burgher/__init__.py
burgher/album.py
burgher/app.py
burgher/blog.py
burgher/context_db.py
burgher/defaults.py
burgher/feed.py
burgher/gallery.py
burgher/hash_utils.py
burgher/node.py
burgher/picture.py
burgher/static.py
burgher/template_nodes.py
burgher/utils.py
burgher/static/album.css
burgher/static/gallery.css
burgher/static/main.css
burgher/templates/album.html
burgher/templates/base.html
burgher/templates/base_bootstrap.html
burgher/templates/gallery.html
burgher/templates/page.html
burgher/templates/includes/chocolat-bottom.html
burgher/templates/includes/chocolat.html
burgher/templates/includes/disqus_comments.html
burgher-1.2.dist-info/LICENSE
burgher-1.2.dist-info/METADATA
burgher-1.2.dist-info/WHEEL
burgher-1.2.dist-info/top_level.txt
burgher-1.2.dist-info/RECORD
