Metadata-Version: 2.1
Name: burgher
Version: 1.2
Summary: Burgher - a static site generator focused on galleries
Author-email: Visgean <visgean@gmail.com>
Project-URL: Homepage, https://github.com/Visgean/burgher
Requires-Python: >=3.12
License-File: LICENSE
Requires-Dist: Jinja2
Requires-Dist: ExifRead
Requires-Dist: feedgen
Requires-Dist: pytz
Requires-Dist: wand
Requires-Dist: progress
Requires-Dist: markdown2
Requires-Dist: python-frontmatter
Requires-Dist: python-slugify
Requires-Dist: pillow ==9.5.0
